bond/__init__.py
bond/__main__.py
bond/app.py
bond/bond
bond/cli/__init__.py
bond/cli/console.py
bond/cli/main.py
bond/cli/table.py
bond/commands/__init__.py
bond/commands/backup.py
bond/commands/discover.py
bond/commands/list.py
bond/commands/livelog.py
bond/commands/reboot.py
bond/commands/reset.py
bond/commands/rfman.py
bond/commands/select.py
bond/commands/signal.py
bond/commands/token.py
bond/commands/upgrade.py
bond/commands/version.py
bond/commands/wifi.py
bond/commands/devices/__init__.py
bond/commands/devices/create.py
bond/commands/devices/delete.py
bond/commands/devices/list.py
bond/commands/groups/__init__.py
bond/commands/groups/create.py
bond/commands/groups/delete.py
bond/commands/groups/list.py
bond/commands/wifi/__init__.py
bond/commands/wifi/connect.py
bond/commands/wifi/shutdown.py
bond/database/__init__.py
bond/database/database.py
bond/database/test_database.py
bond/endpoints/__init__.py
bond/proto/__init__.py
bond/proto/base_transport.py
bond/proto/http.py
bond/proto/mdns.py
bond/proto/wye.py
bond_cli-0.3.0.data/scripts/bond
bond_cli-0.3.0.dist-info/METADATA
bond_cli-0.3.0.dist-info/WHEEL
bond_cli-0.3.0.dist-info/top_level.txt
bond_cli-0.3.0.dist-info/RECORD
