Metadata-Version: 2.1
Name: bond-cli
Version: 0.3.0
Summary: Bond CLI
Author: Olibra
Requires-Python: >=3.7
Requires-Dist: requests
Requires-Dist: zeroconf
